proofnest/__init__.py
proofnest/bitcoin.py
proofnest/cli.py
proofnest/core.py
proofnest/identity.py
proofnest/p2p.py
proofnest/proofbundle.py
proofnest/consensus/__init__.py
proofnest/consensus/block.py
proofnest/consensus/validator.py
proofnest/crypto/__init__.py
proofnest/crypto/constants.py
proofnest/crypto/container.py
proofnest/crypto/dilithium.py
proofnest/crypto/kdf.py
proofnest/crypto/registry.py
proofnest/state/__init__.py
proofnest/state/verkle.py
proofnest-1.2.8.dist-info/METADATA
proofnest-1.2.8.dist-info/WHEEL
proofnest-1.2.8.dist-info/entry_points.txt
proofnest-1.2.8.dist-info/licenses/LICENSE
proofnest-1.2.8.dist-info/RECORD
