Metadata-Version: 2.4
Name: proofnest
Version: 1.2.8
Summary: Proof, not promises. Quantum-ready trust infrastructure for AI agents.
Project-URL: Homepage, https://github.com/proofnest/proofnest
Project-URL: Documentation, https://github.com/proofnest/proofnest#readme
Project-URL: Repository, https://github.com/proofnest/proofnest.git
Project-URL: Issues, https://github.com/proofnest/proofnest/issues
Author-email: Stellanium Ltd <admin@stellanium.io>
Maintainer-email: Stellanium Ltd <admin@stellanium.io>
License: Apache-2.0
License-File: LICENSE
Keywords: accountability,agents,ai,audit,bitcoin,cryptography,decision-logging,post-quantum,proof,transparency,trust,verification
Classifier: Development Status :: 4 - Beta
Classifier: Intended Audience :: Developers
Classifier: Intended Audience :: Science/Research
Classifier: License :: OSI Approved :: Apache Software License
Classifier: Operating System :: OS Independent
Classifier: Programming Language :: Python :: 3
Classifier: Programming Language :: Python :: 3.8
Classifier: Programming Language :: Python :: 3.9
Classifier: Programming Language :: Python :: 3.10
Classifier: Programming Language :: Python :: 3.11
Classifier: Programming Language :: Python :: 3.12
Classifier: Topic :: Scientific/Engineering :: Artificial Intelligence
Classifier: Topic :: Security :: Cryptography
Classifier: Topic :: Software Development :: Libraries :: Python Modules
Classifier: Typing :: Typed
Requires-Python: >=3.8
Requires-Dist: dilithium-py==1.4.0
Requires-Dist: jsonschema>=4.17.0
Requires-Dist: packaging>=21.0
Requires-Dist: pycryptodome>=3.19.0
Requires-Dist: pynacl>=1.5.0
Provides-Extra: bitcoin
Requires-Dist: bitcoinlib>=0.6.0; extra == 'bitcoin'
Provides-Extra: dev
Requires-Dist: black>=23.0; extra == 'dev'
Requires-Dist: cryptography>=41.0.0; extra == 'dev'
Requires-Dist: mypy>=1.0; extra == 'dev'
Requires-Dist: pytest-cov>=4.0; extra == 'dev'
Requires-Dist: pytest>=7.0; extra == 'dev'
Provides-Extra: ed25519
Requires-Dist: cryptography>=41.0.0; extra == 'ed25519'
Provides-Extra: full
Requires-Dist: bitcoinlib>=0.6.0; extra == 'full'
Requires-Dist: cryptography>=41.0.0; extra == 'full'
